herre_next/__init__.py
herre_next/builders.py
herre_next/errors.py
herre_next/herre.py
herre_next/models.py
herre_next/py.typed
herre_next/contrib/__init__.py
herre_next/contrib/rath/__init__.py
herre_next/contrib/rath/auth_link.py
herre_next/fakts/__init__.py
herre_next/fakts/fakts_endpoint_fetcher.py
herre_next/fakts/fakts_qt_store.py
herre_next/fakts/grant.py
herre_next/fakts/registry.py
herre_next/fetcher/__init__.py
herre_next/fetcher/errors.py
herre_next/fetcher/models.py
herre_next/fetcher/userinfo_fetcher.py
herre_next/grants/__init__.py
herre_next/grants/auto_login.py
herre_next/grants/base.py
herre_next/grants/errors.py
herre_next/grants/static.py
herre_next/grants/meta/__init__.py
herre_next/grants/meta/cache.py
herre_next/grants/oauth2/__init__.py
herre_next/grants/oauth2/authorization_code.py
herre_next/grants/oauth2/base.py
herre_next/grants/oauth2/client_credentials.py
herre_next/grants/oauth2/errors.py
herre_next/grants/oauth2/refresh.py
herre_next/grants/oauth2/utils.py
herre_next/grants/oauth2/redirecters/__init__.py
herre_next/grants/oauth2/redirecters/aiohttp_server.py
herre_next/grants/oauth2/redirecters/mock.py
herre_next/grants/oauth2/redirecters/qt_login_view.py
herre_next/grants/qt/auto_login.py
herre_next/grants/qt/errors.py
herre_next/grants/qt/settings_store.py
herre_next-1.3.0.dist-info/METADATA
herre_next-1.3.0.dist-info/WHEEL
herre_next-1.3.0.dist-info/RECORD
