Metadata-Version: 2.4
Name: herre-next
Version: 1.3.0
Summary: asynchronous ouath2 client
Author-email: jhnnsrs <jhnnsrs@gmail.com>
License-Expression: MIT
Requires-Python: >=3.11
Requires-Dist: aiohttp>=3.11.18
Requires-Dist: certifi>=2025.4.26
Requires-Dist: koil>=2.0.4
Requires-Dist: oauthlib>=3.2.2
Requires-Dist: pydantic>2
Requires-Dist: pyyaml>=6.0.2
